emohawk/__init__.py
emohawk/metadata.py
emohawk/version.py
emohawk/readers/__init__.py
emohawk/readers/archive.py
emohawk/readers/csv.py
emohawk/readers/directory.py
emohawk/readers/grib.py
emohawk/readers/json.py
emohawk/readers/netcdf.py
emohawk/readers/shapefile.py
emohawk/readers/zip.py
emohawk/wrappers/__init__.py
emohawk/wrappers/list.py
emohawk/wrappers/numpy.py
emohawk/wrappers/pandas.py
emohawk/wrappers/xarray.py
emohawk-0.0.2.dist-info/LICENSE
emohawk-0.0.2.dist-info/METADATA
emohawk-0.0.2.dist-info/WHEEL
emohawk-0.0.2.dist-info/top_level.txt
emohawk-0.0.2.dist-info/RECORD
